apiget/__init__.py
apiget/apiget.py
apiget-0.0.2.dist-info/METADATA
apiget-0.0.2.dist-info/WHEEL
apiget-0.0.2.dist-info/top_level.txt
apiget-0.0.2.dist-info/RECORD
